odoo/addons/cooperator_info_session/README.rst
odoo/addons/cooperator_info_session/__init__.py
odoo/addons/cooperator_info_session/__manifest__.py
odoo/addons/cooperator_info_session/controllers/__init__.py
odoo/addons/cooperator_info_session/controllers/main.py
odoo/addons/cooperator_info_session/i18n/cooperator_info_session.pot
odoo/addons/cooperator_info_session/i18n/fr.po
odoo/addons/cooperator_info_session/models/__init__.py
odoo/addons/cooperator_info_session/models/res_company.py
odoo/addons/cooperator_info_session/models/res_partner.py
odoo/addons/cooperator_info_session/models/subscription_request.py
odoo/addons/cooperator_info_session/readme/CONTRIBUTORS.rst
odoo/addons/cooperator_info_session/readme/DESCRIPTION.rst
odoo/addons/cooperator_info_session/static/description/index.html
odoo/addons/cooperator_info_session/views/res_company.xml
odoo/addons/cooperator_info_session/views/res_partner.xml
odoo/addons/cooperator_info_session/views/subscription_request.xml
odoo/addons/cooperator_info_session/views/subscription_templates.xml
odoo/addons/cooperator_info_session/wizards/__init__.py
odoo/addons/cooperator_info_session/wizards/beesdoo_shift_subscribe.py
odoo12_addon_cooperator_info_session-12.0.1.0.3.99.dev1.dist-info/METADATA
odoo12_addon_cooperator_info_session-12.0.1.0.3.99.dev1.dist-info/WHEEL
odoo12_addon_cooperator_info_session-12.0.1.0.3.99.dev1.dist-info/top_level.txt
odoo12_addon_cooperator_info_session-12.0.1.0.3.99.dev1.dist-info/RECORD
