Metadata-Version: 2.1
Name: odoo12-addon-cooperator-info-session
Version: 12.0.1.0.3.99.dev1
Summary: Info session for getting share
Home-page: https://github.com/beescoop/Obeesdoo
Author: BEES coop, Coop IT Easy SC
License: AGPL-3
Platform: UNKNOWN
Classifier: Programming Language :: Python
Classifier: Framework :: Odoo
Classifier: Framework :: Odoo :: 12.0
Classifier: License :: OSI Approved :: GNU Affero General Public License v3
Requires-Python: >=3.5
Requires-Dist: odoo12-addon-cooperator
Requires-Dist: odoo12-addon-cooperator-website
Requires-Dist: odoo12-addon-shift
Requires-Dist: odoo (<12.1dev,>=12.0a)
